common/__init__.py
common/lang.py
common/model.py
common/text_utils.py
common_aiqingyuyan-0.0.1.dist-info/LICENSE
common_aiqingyuyan-0.0.1.dist-info/METADATA
common_aiqingyuyan-0.0.1.dist-info/WHEEL
common_aiqingyuyan-0.0.1.dist-info/top_level.txt
common_aiqingyuyan-0.0.1.dist-info/RECORD
