Metadata-Version: 2.1
Name: common-aiqingyuyan
Version: 0.0.1
Summary: Common package
Home-page: UNKNOWN
Author: Yan
Author-email: aiqingyuyan911@gmail.com
License: UNKNOWN
Platform: UNKNOWN
Classifier: Programming Language :: Python :: 3
Classifier: License :: OSI Approved :: MIT License
Classifier: Operating System :: OS Independent
Requires-Python: >=3.6
